investani/__init__.py
investani/get_share_holder.py
investani/jup_reader.py
investani-0.0.1.dist-info/LICENSE
investani-0.0.1.dist-info/METADATA
investani-0.0.1.dist-info/WHEEL
investani-0.0.1.dist-info/top_level.txt
investani-0.0.1.dist-info/RECORD
