Metadata-Version: 2.1
Name: investani
Version: 0.0.1
Summary: A package that expected to help people analyze the company for investment.
Home-page: https://github.com/noppGithub/investani
Author: Nopporn Phantawee
Author-email: n.phantawee@gmail.com
License: MIT
Platform: UNKNOWN
Classifier: Development Status :: 3 - Alpha
Classifier: Intended Audience :: Developers
Classifier: License :: OSI Approved :: MIT License
Classifier: Operating System :: OS Independent
Classifier: Programming Language :: Python :: 3
Classifier: Programming Language :: Python :: 3.6
Classifier: Programming Language :: Python :: 3.7
Classifier: Programming Language :: Python :: 3.8
Classifier: Programming Language :: Python :: 3.9
Classifier: Programming Language :: Python :: 3 :: Only
Requires-Python: >=3.6, <4
License-File: LICENSE
Requires-Dist: bs4 (==0.0.1)
Requires-Dist: pandas (>=1.1.0)
Requires-Dist: PyYAML (>=6.0)
Requires-Dist: requests (>=2.20.1)
Requires-Dist: scikit-learn (>=1.0.0)
Provides-Extra: dev
Requires-Dist: check-manifest ; extra == 'dev'
Provides-Extra: test
Requires-Dist: coverage ; extra == 'test'
